gdocsync/__init__.py
gdocsync/cli.py
gdocsync/constants.py
gdocsync/docs_importer.py
gdocsync/google_drive_client.py
gdocsync/html_cleaner.py
gdocsync/johnny_decimal.py
gdocsync/pandoc_client.py
gdocsync/regexes.py
gdocsync/shelve_cache.py
gdocsync-0.2.0.dist-info/LICENSE
gdocsync-0.2.0.dist-info/METADATA
gdocsync-0.2.0.dist-info/WHEEL
gdocsync-0.2.0.dist-info/entry_points.txt
gdocsync-0.2.0.dist-info/top_level.txt
gdocsync-0.2.0.dist-info/RECORD
